{"cameraMode":{"drawMode":0,"name":"Shaded","section":"Shading Mode"},"sceneLighting":true,"audioPlay":false,"sceneViewState":{"showFog":true,"showMaterialUpdate":false,"showSkybox":true,"showFlares":true,"showImageEffects":true,"showParticleSystems":true},"in2DMode":false,"pivot":{"x":0.1188831627368927,"y":5.509591579437256,"z":-9.038799285888672},"rotation":{"x":0.2479477971792221,"y":-0.5374388694763184,"z":0.16908492147922517,"w":0.788100004196167},"size":3.3191349506378176,"orthographic":false}